nyle/__init__.py
nyle/__main__.py
nyle/_version.py
nyle/git.py
nyle/py.typed
nyle/tagger.py
nyle-0.0.2.dist-info/METADATA
nyle-0.0.2.dist-info/WHEEL
nyle-0.0.2.dist-info/entry_points.txt
nyle-0.0.2.dist-info/licenses/LICENSE.txt
nyle-0.0.2.dist-info/RECORD
